activity_list/__init__.py
activity_list/admin.py
activity_list/apps.py
activity_list/locale/my/LC_MESSAGES/django.po
activity_list/locale/ru/LC_MESSAGES/django.po
activity_list/locale/tm/LC_MESSAGES/django.po
activity_list/locale/uz/LC_MESSAGES/django.po
activity_list/migrations/__init__.py
activity_list/models.py
activity_list/static/activity_list/activity_list_store.js
activity_list/templates/activity_list/activity_list.html
activity_list/templates/activity_list/download_icon.svg
activity_list/templates/activity_list/filters_icon.svg
activity_list/templates/riottags/activity-list-paginate.html
activity_list/templates/riottags/project-list-filter.html
activity_list/tests.py
activity_list/urls.py
activity_list/views.py
activity_profile/__init__.py
activity_profile/apps.py
activity_profile/locale/my/LC_MESSAGES/django.po
activity_profile/locale/ru/LC_MESSAGES/django.po
activity_profile/locale/tm/LC_MESSAGES/django.po
activity_profile/locale/uz/LC_MESSAGES/django.po
activity_profile/migrations/0001_initial.py
activity_profile/migrations/0002_drop_activity_key.py
activity_profile/migrations/0003_recreate_activity_pk.py
activity_profile/migrations/__init__.py
activity_profile/models.py
activity_profile/templates/activity_profile/activity_profile.html
activity_profile/templates/activity_profile/profile_base.html
activity_profile/templates/tags/about_activity.html
activity_profile/templates/tags/about_activity.js
activity_profile/templates/tags/activity_banner.html
activity_profile/templates/tags/activity_banner.js
activity_profile/templates/tags/activity_financials.html
activity_profile/templates/tags/activity_financials.js
activity_profile/templates/tags/activity_locations_map.html
activity_profile/templates/tags/activity_tags.html
activity_profile/templates/tags/contacts.html
activity_profile/templates/tags/contacts.js
activity_profile/templates/tags/description_field.html
activity_profile/templates/tags/documents.html
activity_profile/templates/tags/documents.js
openly-0.1.4.dist-info/WHEEL
openly-0.1.4.dist-info/METADATA
openly-0.1.4.dist-info/RECORD
