Metadata-Version: 2.1
Name: openly
Version: 0.1.4
Summary: 
Author: Josh Brooks
Author-email: josh@catalpa.io
Requires-Python: >=3.8,<4.0
Classifier: Programming Language :: Python :: 3
Classifier: Programming Language :: Python :: 3.10
Classifier: Programming Language :: Python :: 3.8
Classifier: Programming Language :: Python :: 3.9
Requires-Dist: Django (<3.2)
Requires-Dist: Pillow (>=9.0.1,<10.0.0)
Requires-Dist: Whoosh (>=2.7.4,<3.0.0)
Requires-Dist: celery (>=5.2.3,<6.0.0)
Requires-Dist: django-crispy-forms (>=1.14.0,<2.0.0)
Requires-Dist: django-el-pagination (>=3.3.0,<4.0.0)
Requires-Dist: django-geojson (>=3.2.1,<4.0.0)
Requires-Dist: django-haystack (>=3.1.1,<4.0.0)
Requires-Dist: django-leaflet (>=0.28.2,<0.29.0)
Requires-Dist: django-model-utils (>=4.2.0,<5.0.0)
Requires-Dist: django-modeltranslation (>=0.17.5,<0.18.0)
Requires-Dist: django-registration-redux (>=2.10,<3.0)
Requires-Dist: django-widget-tweaks (>=1.4.12,<2.0.0)
Requires-Dist: djangorestframework (>=3.13.1,<4.0.0)
Requires-Dist: requests (>=2.27.1,<3.0.0)
Requires-Dist: sentry-sdk (>=1.5.8,<2.0.0)
Requires-Dist: simple-locations (>=3.1.3,<4.0.0)
Requires-Dist: urllib3 (<1.26)
